opencve/VERSION
opencve/__init__.py
opencve/admin.py
opencve/app.py
opencve/cli.py
opencve/configuration.py
opencve/constants.py
opencve/context.py
opencve/default.cfg
opencve/extensions.py
opencve/forms.py
opencve/settings.py
opencve/utils.py
opencve/api/__init__.py
opencve/api/alerts.py
opencve/api/base.py
opencve/api/cves.py
opencve/api/cwes.py
opencve/api/fields.py
opencve/api/products.py
opencve/api/reports.py
opencve/api/subscriptions.py
opencve/api/vendors.py
opencve/checks/__init__.py
opencve/checks/cpes.py
opencve/checks/cvss.py
opencve/checks/cwes.py
opencve/checks/first_time.py
opencve/checks/references.py
opencve/checks/summary.py
opencve/commands/__init__.py
opencve/commands/celery.py
opencve/commands/create_user.py
opencve/commands/init.py
opencve/commands/migrate_nvd.py
opencve/commands/upgrade_db.py
opencve/commands/utils.py
opencve/commands/webserver.py
opencve/commands/imports/__init__.py
opencve/commands/imports/cve.py
opencve/commands/imports/cwe.py
opencve/controllers/__init__.py
opencve/controllers/alerts.py
opencve/controllers/base.py
opencve/controllers/cves.py
opencve/controllers/cwes.py
opencve/controllers/home.py
opencve/controllers/main.py
opencve/controllers/products.py
opencve/controllers/reports.py
opencve/controllers/subscriptions.py
opencve/controllers/tags.py
opencve/controllers/vendors.py
opencve/migrations/README
opencve/migrations/alembic.ini
opencve/migrations/env.py
opencve/migrations/script.py.mako
opencve/migrations/versions/0bcd7a25924a_migrate_nvd_format.py
opencve/migrations/versions/1c7aecfc5f6e_add_indexes_cascade_deletions_reports.py
opencve/migrations/versions/2132d05ea0e2_add_first_time_value_in_event_types_enum.py
opencve/migrations/versions/33cd640e1112_add_indexes_on_cves_summary_and_cve_cve_.py
opencve/migrations/versions/3f755e0484e0_add_settings_columns_in_users_table.py
opencve/migrations/versions/4195eeb432e9_add_tags_tables.py
opencve/migrations/versions/41ad8e9163d4_make_cwe_cwe_id_field_not_nullable.py
opencve-1.5.0.dist-info/LICENSE
opencve-1.5.0.dist-info/METADATA
opencve-1.5.0.dist-info/WHEEL
opencve-1.5.0.dist-info/entry_points.txt
opencve-1.5.0.dist-info/top_level.txt
opencve-1.5.0.dist-info/RECORD
