Metadata-Version: 2.1
Name: opencve
Version: 1.5.0
Summary: CVE Alerting Platform
Home-page: https://github.com/opencve/opencve
Author: Nicolas Crocfer
Author-email: ncrocfer@gmail.com
Classifier: Development Status :: 4 - Beta
Classifier: Environment :: Console
Classifier: Environment :: Web Environment
Classifier: License :: OSI Approved :: BSD License
Classifier: Programming Language :: Python :: 3
Classifier: Programming Language :: Python :: 3.7
Classifier: Programming Language :: Python :: 3.8
Requires-Python: >=3.7
License-File: LICENSE
Requires-Dist: Flask ==1.0.2
Requires-Dist: Flask-Admin ==1.5.5
Requires-Dist: Flask-Assets ==0.12
Requires-Dist: Flask-DebugToolbar ==0.10.1
Requires-Dist: Flask-SQLAlchemy ==2.3.2
Requires-Dist: Flask-Migrate ==3.0.1
Requires-Dist: Flask-Login ==0.4.1
Requires-Dist: Flask-WTF ==0.14.3
Requires-Dist: Flask-User ==1.0.2.2
Requires-Dist: Flask-Gravatar ==0.5.0
Requires-Dist: Flask-Paginate ==0.5.2
Requires-Dist: Flask-RESTful ==0.3.8
Requires-Dist: Flask-Limiter ==1.4
Requires-Dist: SQLAlchemy ==1.3.1
Requires-Dist: SQLAlchemy-Utils ==0.33.11
Requires-Dist: psycopg2-binary ==2.8.4
Requires-Dist: Redis ==3.3.11
Requires-Dist: arrow ==0.13.1
Requires-Dist: celery ==4.3.0
Requires-Dist: cpe ==1.2.1
Requires-Dist: untangle ==1.1.1
Requires-Dist: cssmin ==0.2.0
Requires-Dist: jsmin ==3.0.1
Requires-Dist: requests ==2.23.0
Requires-Dist: nested-lookup ==0.2.18
Requires-Dist: deepdiff ==4.0.7
Requires-Dist: gunicorn ==20.0.4
Requires-Dist: vine ==1.3.0
Requires-Dist: click ==7.1.2
Requires-Dist: werkzeug ==1.0.1
Requires-Dist: itsdangerous ==1.1.0
Requires-Dist: markupSafe ==1.1.1
Requires-Dist: jinja2 ==2.11.3
Requires-Dist: importlib-metadata ==4.13.0
Requires-Dist: email-validator ==1.1.0
Provides-Extra: dev
Requires-Dist: pytest ==5.4.1 ; extra == 'dev'
Requires-Dist: pytest-cov ==2.11.1 ; extra == 'dev'
Requires-Dist: pytest-freezegun ==0.4.2 ; extra == 'dev'
Requires-Dist: black ==20.8b1 ; extra == 'dev'
Requires-Dist: beautifulsoup4 ==4.9.3 ; extra == 'dev'
Provides-Extra: sendmail
Requires-Dist: Flask-Sendmail-ng ==0.3 ; extra == 'sendmail'
